Workbook

Sheet Read Me
A1: Corporate Treasury & Liquidity Analysis: Infosys Ltd.
A2: Single-source edition · FY2022-23 to FY2024-25 · ₹ crore · built only from Infosys 'Additional Information' (Annual Report 2024-25 extract)
A4: Purpose | B4: Assess how Infosys generates and holds cash and how its liquidity position changed over three years, using only the figures printed in one public document.
A5: Source | B5: Infosys Limited, 'Additional Information' (7-page extract of the Annual Report 2024-25; file infosys.pdf). Page numbers in 'Raw Data' refer to its printed pages. No other source is used.
A6: Basis | B6: Ratios on p.1 are stated to be based on consolidated IFRS INR statements. The Historical Data table (p.4) names no basis. Figures are used exactly as printed.
A7: What this edition can do | B7: Cash and investments, net cash, cover of operating costs, net current assets, capital intensity, profitability checks, trends, and an approximate operating cash flow and free cash flow rebuilt from the printed OCF ÷ revenue ratio (with a rounding range).
A8: What it cannot do | B8: Current ratio, cash ratio, OCF ratio and quick ratio need total current assets and current liabilities, which the source does not give. They are shown as NOT AVAILABLE, not estimated. Dividends, buy-backs, lease payments and tax paid cannot be itemised.
A9: Sheets | B9: Raw Data → Financial Calculations → Trend Analysis → Dashboard → Data Sources and Audit Checks. Change a blue cell and everything downstream recalculates.
A10: Key cautions | B10: (1) Accounting basis: p.1 says the ratios use consolidated IFRS INR statements; the Historical Data table (p.4) does not name its basis. All figures are used as printed. (2) Rounding: ratios are printed to one decimal place (0.1 percentage point), so any rupee figure rebuilt from a ratio can be off by up to +/-0.05 percentage point of the base (about +/-Rs 80 crore on FY25 revenue). (3) Non-IFRS measure: the company's 'cash and investments' (p.1) excludes some investments; footnotes on p.1 and p.2 word the exclusion slightly differently. (4) Investments are shown as one combined current + non-current line, so cash + investments cannot be treated as a current-asset (short-term) measure.
A11: Preparation note | B11: Prepared by Bhargava C as an independent academic project.see README. Not investment advice.

Sheet Raw Data
A1: Raw Data - figures typed from the source PDF
A2: Source: Infosys Limited, 'Additional Information' (Annual Report 2024-25 extract; file infosys.pdf). Blue = typed input. Nothing on this sheet is estimated.
A3: Units: ₹ crore unless stated. Ratios are stored as decimals and shown as %. Page numbers are the printed page numbers of the PDF (p.1-p.7).
A4: Ref | B4: Item | C4: FY2022-23 | D4: FY2023-24 | E4: FY2024-25 | F4: Unit | G4: Type | H4: PDF page | I4: Table in PDF | J4: Notes
A5: A. Financial performance (Rs crore) - Historical Data table
A6: R01 | B6: Revenue | C6: 146767 | D6: 153670 | E6: 162990 | F6: ₹ crore | G6: Reported | H6: p.4 | I6: Historical Data
A7: R02 | B7: Operating profit | C7: 30905 | D7: 31747 | E7: 34424 | F7: ₹ crore | G7: Reported | H7: p.4 | I7: Historical Data | J7: Before other income and finance cost (file does not give a definition).
A8: R03 | B8: Finance cost | C8: 284 | D8: 470 | E8: 416 | F8: ₹ crore | G8: Reported | H8: p.4 | I8: Historical Data | J8: Debt is nil in the same table, so the file does not show what this cost relates to.
A9: R04 | B9: Profit before income taxes (PBT) | C9: 33322 | D9: 35988 | E9: 37608 | F9: ₹ crore | G9: Reported | H9: p.4 | I9: Historical Data
A10: R05 | B10: Provision for taxation | C10: 9214 | D10: 9740 | E10: 10858 | F10: ₹ crore | G10: Reported | H10: p.4 | I10: Historical Data
A11: R06 | B11: Profit after tax (PAT) | C11: 24108 | D11: 26248 | E11: 26750 | F11: ₹ crore | G11: Reported | H11: p.4 | I11: Historical Data
A12: R07 | B12: Profit attributable to non-controlling interests | C12: 13 | D12: 15 | E12: 37 | F12: ₹ crore | G12: Reported | H12: p.4 | I12: Historical Data
A13: R08 | B13: Profit attributable to owners of the Company | C13: 24095 | D13: 26233 | E13: 26713 | F13: ₹ crore | G13: Reported | H13: p.4 | I13: Historical Data
A14: B. Financial position and capital expenditure (Rs crore) - Historical Data table
A15: R10 | B15: Equity | C15: 75795 | D15: 88461 | E15: 96203 | F15: ₹ crore | G15: Reported | H15: p.4 | I15: Historical Data
A16: R11 | B16: Debt | C16: 0 | D16: 0 | E16: 0 | F16: ₹ crore | G16: Reported | H16: p.4 | I16: Historical Data | J16: Printed as a dash (nil) in every year from 2014 to 2025; entered as 0.
A17: R12 | B17: Property, plant and equipment | C17: 13793 | D17: 12818 | E17: 12800 | F17: ₹ crore | G17: Reported | H17: p.4 | I17: Historical Data
A18: R13 | B18: Right-of-use assets | C18: 6882 | D18: 6552 | E18: 6311 | F18: ₹ crore | G18: Reported | H18: p.4 | I18: Historical Data
A19: R14 | B19: Capital expenditure | C19: 2579 | D19: 2201 | E19: 2237 | F19: ₹ crore | G19: Reported | H19: p.4 | I19: Historical Data | J19: Definition not given in the file (cash outflow vs. additions not stated).
A20: R15 | B20: Cash and cash equivalents | C20: 12173 | D20: 14786 | E20: 24455 | F20: ₹ crore | G20: Reported | H20: p.4 | I20: Historical Data
A21: R16 | B21: Current and non-current investments | C21: 19478 | D21: 24623 | E21: 23541 | F21: ₹ crore | G21: Reported | H21: p.4 | I21: Historical Data | J21: Current and non-current are combined in one line; the split is not in the file.
A22: R17 | B22: Net current assets | C22: 31695 | D22: 50638 | E22: 54249 | F22: ₹ crore | G22: Reported | H22: p.4 | I22: Historical Data | J22: Definition not given; understood as current assets less current liabilities. Neither component is in the file.
A23: R18 | B23: Total assets | C23: 125816 | D23: 137814 | E23: 148903 | F23: ₹ crore | G23: Reported | H23: p.4 | I23: Historical Data
A24: R19 | B24: Market capitalisation - period end | C24: 592394 | D24: 621821 | E24: 652332 | F24: ₹ crore | G24: Reported | H24: p.4 | I24: Historical Data | J24: Context only; not used in liquidity metrics.
A25: C. Reported ratios - Ratio analysis table (p.1; stored as decimals, one decimal place in the file)
A26: Q01 | B26: Operating cash flows / revenue | C26: 0.157 | D26: 0.17 | E26: 0.226 | F26: % | G26: Reported ratio | H26: p.1 | I26: Ratio analysis | J26: The ONLY cash-flow-statement information in the file. Rounded to 0.1 percentage point.
A27: Q02 | B27: Consolidated cash and investments / total assets | C27: 0.249 | D27: 0.283 | E27: 0.319 | F27: % | G27: Reported ratio | H27: p.1 | I27: Ratio analysis | J27: Non-IFRS measure; footnote (2) on p.1 lists items excluded (equity/preference shares, unquoted CCDs, others).
A28: Q03 | B28: Consolidated cash and investments / revenue | C28: 0.213 | D28: 0.254 | E28: 0.292 | F28: % | G28: Reported ratio | H28: p.1 | I28: Ratio analysis | J28: Same non-IFRS definition as Q02.
A29: Q04 | B29: Day's sales outstanding (USD terms) | C29: 62 | D29: 71 | E29: 69 | F29: days | G29: Reported ratio | H29: p.1 | I29: Ratio analysis | J29: Computed by the company in USD terms.
A30: Q05 | B30: Operating profit / revenue | C30: 0.211 | D30: 0.207 | E30: 0.211 | F30: % | G30: Reported ratio | H30: p.1 | I30: Ratio analysis
A31: Q06 | B31: Other income / revenue | C31: 0.018 | D31: 0.031 | E31: 0.022 | F31: % | G31: Reported ratio | H31: p.1 | I31: Ratio analysis
A32: Q07 | B32: Profit before tax (PBT) / revenue | C32: 0.227 | D32: 0.234 | E32: 0.231 | F32: % | G32: Reported ratio | H32: p.1 | I32: Ratio analysis
A33: Q08 | B33: Tax / revenue | C33: 0.063 | D33: 0.063 | E33: 0.067 | F33: % | G33: Reported ratio | H33: p.1 | I33: Ratio analysis
A34: Q09 | B34: Effective tax rate (tax / PBT) | C34: 0.277 | D34: 0.271 | E34: 0.289 | F34: % | G34: Reported ratio | H34: p.1 | I34: Ratio analysis
A35: Q10 | B35: Profit after tax (PAT) / revenue | C35: 0.164 | D35: 0.171 | E35: 0.164 | F35: % | G35: Reported ratio | H35: p.1 | I35: Ratio analysis
A36: Q11 | B36: Return on equity (USD terms) | C36: 0.312 | D36: 0.321 | E36: 0.29 | F36: % | G36: Reported ratio | H36: p.1 | I36: Ratio analysis | J36: USD terms; cannot be recomputed from rupee figures in the file.
A37: Q12 | B37: Dividend payout | C37: 0.695 | D37: 0.8 | E37: 0.517 | F37: % | G37: Reported ratio | H37: p.1 | I37: Ratio analysis | J37: Definition and rupee amount of dividends are not in the file.
A38: Q13 | B38: Market capitalisation / revenue (times) | C38: 4 | D38: 4 | E38: 4 | F38: x | G38: Reported ratio | H38: p.1 | I38: Ratio analysis | J38: Context only.
A39: Q14 | B39: Cost of sales / revenue | C39: 0.697 | D39: 0.699 | E39: 0.695 | F39: % | G39: Reported ratio | H39: p.1 | I39: Ratio analysis
A40: Q16 | B40: Export revenue / revenue | C40: 0.974 | D40: 0.975 | E40: 0.969 | F40: % | G40: Reported ratio | H40: p.1 | I40: Ratio analysis | J40: The file does not define 'export revenue' or give its currency mix.
A41: Q15 | B41: Aggregate employee costs / revenue | C41: 0.534 | D41: 0.538 | E41: 0.527 | F41: % | G41: Reported ratio | H41: p.1 | I41: Ratio analysis
A42: D. Per-share data and growth (p.3 and p.4)
A43: S01 | B43: Basic EPS | C43: 57.63 | D43: 63.39 | E43: 64.5 | F43: ₹ | G43: Reported | H43: p.4 | I43: Historical Data | J43: Same values on p.1.
A44: S02 | B44: Book value per share | C44: 182 | D44: 213 | E44: 231 | F44: ₹ | G44: Reported | H44: p.4 | I44: Historical Data
A45: G01 | B45: Revenue growth, as printed (₹ crore basis) | C45: 0.21 | D45: 0.05 | E45: 0.06 | F45: % | G45: Reported | H45: p.3 | I45: Employee strength and revenue growth | J45: Printed as whole percentages.
A46: G02 | B46: PAT growth, as printed (₹ crore basis) | C46: 0.09 | D46: 0.09 | E46: 0.02 | F46: % | G46: Reported | H46: p.3 | I46: Employee strength and revenue growth | J46: Printed as whole percentages.
A47: E. Cross-page copies and prior-year references (used only by audit checks)
A48: X01 | B48: Revenue as shown in the growth table | C48: 146767 | D48: 153670 | E48: 162990 | F48: ₹ crore | G48: Reported | H48: p.3 | I48: Employee strength and revenue growth | J48: Second appearance of revenue; compared with R01 by an audit check.
A49: X02 | B49: PAT as shown in the growth table | C49: 24108 | D49: 26248 | E49: 26750 | F49: ₹ crore | G49: Reported | H49: p.3 | I49: Employee strength and revenue growth | J49: Second appearance of PAT; compared with R06.
A50: X03 | B50: Revenue, previous financial year | C50: 121641 | D50: 146767 | E50: 153670 | F50: ₹ crore | G50: Reported | H50: p.3 | I50: Employee strength and revenue growth | J50: FY2021-22 revenue is printed on p.3 and p.4; FY23/FY24 values repeat R01.
A51: X04 | B51: PAT, previous financial year | C51: 22146 | D51: 24108 | E51: 26248 | F51: ₹ crore | G51: Reported | H51: p.3 | I51: Employee strength and revenue growth | J51: FY2021-22 PAT is printed on p.3 and p.4.
A52: X05 | B52: Employees at year end (Infosys Group) | C52: 343234 | D52: 317240 | E52: 323578 | F52: count | G52: Reported | H52: p.3 | I52: Employee strength and revenue growth | J52: Context only.
A53: X06 | B53: Revenue (USD million, IFRS) | C53: 18212 | D53: 18562 | E53: 19277 | F53: USD million | G53: Reported | H53: p.3 | I53: Employee strength and revenue growth | J53: Context only.
A54: F. Credit ratings (text; p.4)
A55: T01 | B55: Standard & Poor's | C55: A | D55: A | E55: A | F55: text | G55: Reported text | H55: p.4 | I55: Historical Data
A56: T02 | B56: CRISIL | C56: AAA | D56: AAA | E56: AAA | F56: text | G56: Reported text | H56: p.4 | I56: Historical Data
A57: T03 | B57: Moody's | C57: Baa1 | D57: Baa1 | E57: Baa1 | F57: text | G57: Reported text | H57: p.4 | I57: Historical Data
A58: T04 | B58: Dun & Bradstreet | C58: 5A1 | D58: 5A1 | E58: 5A1 | F58: text | G58: Reported text | H58: p.4 | I58: Historical Data
A60: Not in the source (so not on this sheet): operating cash flow in ₹, total current assets, total current liabilities, free cash flow, dividends and buy-back amounts. See 'Financial Calculations', Part F.

Sheet Financial Calculations
A1: Financial Calculations
A2: Green = link to Raw Data. Black = formula. Rows marked DERIVED use the printed (rounded) OCF/revenue ratio and are approximate; their range is shown explicitly.
A4: Ref | B4: Metric | C4: FY2022-23 | D4: FY2023-24 | E4: FY2024-25 | F4: Unit | G4: Basis | H4: How it is calculated | I4: Reading / caution
A5: Assumptions (blue = editable)
A6: AS1 | B6: Rounding tolerance on printed ratios (± as a decimal; 0.0005 = ±0.05 percentage point) | C6: 0.0005 | H6: Ratios in the PDF are printed to 0.1 pp, so the true value lies within ±0.05 pp of the printed one.
A7: AS2 | B7: Days in a year (for per-day operating cost) | C7: 365
A8: A. Cash and investments (reported inputs)
A9: A01 | B9: Cash and cash equivalents | C9: ='Raw Data'!C20 -> 12173 | D9: ='Raw Data'!D20 -> 14786 | E9: ='Raw Data'!E20 -> 24455 | F9: ₹ crore | G9: Reported | H9: Raw Data R15
A10: A02 | B10: Investments (current + non-current) | C10: ='Raw Data'!C21 -> 19478 | D10: ='Raw Data'!D21 -> 24623 | E10: ='Raw Data'!E21 -> 23541 | F10: ₹ crore | G10: Reported | H10: Raw Data R16 | I10: Current and non-current are combined in the source; the split is not available.
A11: A03 | B11: Cash + investments | C11: =C9+C10 -> 31651 | D11: =D9+D10 -> 39409 | E11: =E9+E10 -> 47996 | F11: ₹ crore | G11: Calculated | H11: A01 + A02 | I11: Broad measure. It includes non-current investments, so it is NOT a short-term (current-asset) measure.
A12: A04 | B12: Net cash (cash + investments − debt) | C12: =C11-'Raw Data'!C16 -> 31651 | D12: =D11-'Raw Data'!D16 -> 39409 | E12: =E11-'Raw Data'!E16 -> 47996 | F12: ₹ crore | G12: Calculated | H12: A03 − Debt (R11) | I12: Debt is nil in all three years, so net cash equals cash + investments.
A13: A05 | B13: Cash and equivalents as % of cash + investments | C13: =IFERROR(C9/C11,"n.a.") -> 0.3846008 | D13: =IFERROR(D9/D11,"n.a.") -> 0.37519348 | E13: =IFERROR(E9/E11,"n.a.") -> 0.50952163 | F13: % | G13: Calculated | H13: A01 ÷ A03 | I13: Higher share = more of the pool is held as cash rather than investments.
A14: A06 | B14: Cash + investments ÷ total assets (own calculation) | C14: =IFERROR(C11/'Raw Data'!C23,"n.a.") -> 0.25156578 | D14: =IFERROR(D11/'Raw Data'!D23,"n.a.") -> 0.28595789 | E14: =IFERROR(E11/'Raw Data'!E23,"n.a.") -> 0.32233064 | F14: % | G14: Calculated | H14: A03 ÷ Total assets (R18) | I14: Slightly above the company's figure because the company excludes some investments (see A07).
A15: A07 | B15: Cash and investments ÷ total assets (company, printed) | C15: ='Raw Data'!C27 -> 0.249 | D15: ='Raw Data'!D27 -> 0.283 | E15: ='Raw Data'!E27 -> 0.319 | F15: % | G15: Reported ratio | H15: Raw Data Q02 | I15: Company's non-IFRS measure (p.1).
A16: A08 | B16: Gap: own less company | C16: =(C14-C15)*100 -> 0.25657786 | D16: =(D14-D15)*100 -> 0.29578853 | E16: =(E14-E15)*100 -> 0.33306448 | F16: pp | G16: Check | H16: (A06 − A07) × 100 | I16: A small positive gap is expected; a large or negative gap would signal a data problem.
A17: A09 | B17: Cash + investments ÷ revenue (own calculation) | C17: =IFERROR(C11/'Raw Data'!C6,"n.a.") -> 0.21565475 | D17: =IFERROR(D11/'Raw Data'!D6,"n.a.") -> 0.25645214 | E17: =IFERROR(E11/'Raw Data'!E6,"n.a.") -> 0.29447205 | F17: % | G17: Calculated | H17: A03 ÷ Revenue (R01)
A18: A10 | B18: Cash and investments ÷ revenue (company, printed) | C18: ='Raw Data'!C28 -> 0.213 | D18: ='Raw Data'!D28 -> 0.254 | E18: ='Raw Data'!E28 -> 0.292 | F18: % | G18: Reported ratio | H18: Raw Data Q03
A19: A11 | B19: Gap: own less company | C19: =(C17-C18)*100 -> 0.26547453 | D19: =(D17-D18)*100 -> 0.24521377 | E19: =(E17-E18)*100 -> 0.24720535 | F19: pp | G19: Check | H19: (A09 − A10) × 100
A20: B. Working capital, solvency and operating-cost cover
A21: B01 | B21: Net current assets | C21: ='Raw Data'!C22 -> 31695 | D21: ='Raw Data'!D22 -> 50638 | E21: ='Raw Data'!E22 -> 54249 | F21: ₹ crore | G21: Reported | H21: Raw Data R17 | I21: Source does not define it or give its two components; used only as reported.
A22: B02 | B22: Net current assets ÷ revenue | C22: =IFERROR(C21/'Raw Data'!C6,"n.a.") -> 0.21595454 | D22: =IFERROR(D21/'Raw Data'!D6,"n.a.") -> 0.32952431 | E22: =IFERROR(E21/'Raw Data'!E6,"n.a.") -> 0.33283637 | F22: % | G22: Calculated | H22: B01 ÷ Revenue
A23: B03 | B23: Net current assets ÷ total assets | C23: =IFERROR(C21/'Raw Data'!C23,"n.a.") -> 0.2519155 | D23: =IFERROR(D21/'Raw Data'!D23,"n.a.") -> 0.36743727 | E23: =IFERROR(E21/'Raw Data'!E23,"n.a.") -> 0.36432443 | F23: % | G23: Calculated | H23: B01 ÷ Total assets
A24: B04 | B24: Equity ÷ total assets | C24: =IFERROR('Raw Data'!C15/'Raw Data'!C23,"n.a.") -> 0.60242735 | D24: =IFERROR('Raw Data'!D15/'Raw Data'!D23,"n.a.") -> 0.64188689 | E24: =IFERROR('Raw Data'!E15/'Raw Data'!E23,"n.a.") -> 0.64607832 | F24: % | G24: Calculated | H24: Equity (R10) ÷ Total assets (R18) | I24: Rising share of equity = less reliance on liabilities.
A25: B05 | B25: Debt ÷ equity | C25: =IFERROR('Raw Data'!C16/'Raw Data'!C15,"n.a.") -> 0 | D25: =IFERROR('Raw Data'!D16/'Raw Data'!D15,"n.a.") -> 0 | E25: =IFERROR('Raw Data'!E16/'Raw Data'!E15,"n.a.") -> 0 | F25: x | G25: Calculated | H25: Debt (R11) ÷ Equity (R10) | I25: Zero: the source shows no debt in any year.
A26: B06 | B26: Finance cost | C26: ='Raw Data'!C8 -> 284 | D26: ='Raw Data'!D8 -> 470 | E26: ='Raw Data'!E8 -> 416 | F26: ₹ crore | G26: Reported | H26: Raw Data R03 | I26: A positive finance cost alongside nil debt means it relates to something other than borrowings; the source does not say what.
A27: B07 | B27: Operating profit ÷ finance cost | C27: =IFERROR('Raw Data'!C7/C26,"n.a.") -> 108.82042 | D27: =IFERROR('Raw Data'!D7/D26,"n.a.") -> 67.546809 | E27: =IFERROR('Raw Data'!E7/E26,"n.a.") -> 82.75 | F27: x | G27: Calculated | H27: Operating profit (R02) ÷ B06 | I27: Coverage is very high in every year.
A28: B08 | B28: Operating costs (revenue − operating profit) | C28: ='Raw Data'!C6-'Raw Data'!C7 -> 115862 | D28: ='Raw Data'!D6-'Raw Data'!D7 -> 121923 | E28: ='Raw Data'!E6-'Raw Data'!E7 -> 128566 | F28: ₹ crore | G28: Calculated | H28: Revenue (R01) − Operating profit (R02) | I28: Includes non-cash items such as depreciation, so cash costs are somewhat lower (cover days below are conservative).
A29: B09 | B29: Operating costs per day | C29: =C28/$C$7 -> 317.43014 | D29: =D28/$C$7 -> 334.03562 | E29: =E28/$C$7 -> 352.23562 | F29: ₹ crore | G29: Calculated | H29: B08 ÷ days in year (AS2)
A30: B10 | B30: Days of operating costs covered by cash + investments | C30: =IFERROR(C11/C29,"n.a.") -> 99.710129 | D30: =IFERROR(D11/D29,"n.a.") -> 117.97844 | E30: =IFERROR(E11/E29,"n.a.") -> 136.26106 | F30: days | G30: Calculated | H30: A03 ÷ B09 | I30: A buffer measure: how long the pool would fund operating costs with no revenue.
A31: B11 | B31: Days of operating costs covered by cash and equivalents only | C31: =IFERROR(C9/C29,"n.a.") -> 38.348596 | D31: =IFERROR(D9/D29,"n.a.") -> 44.264741 | E31: =IFERROR(E9/E29,"n.a.") -> 69.427959 | F31: days | G31: Calculated | H31: A01 ÷ B09 | I31: The stricter, more immediately available version.
A32: B12 | B32: Day's sales outstanding (company, USD terms) | C32: ='Raw Data'!C29 -> 62 | D32: ='Raw Data'!D29 -> 71 | E32: ='Raw Data'!E29 -> 69 | F32: days | G32: Reported ratio | H32: Raw Data Q04 | I32: Lower = faster collection. Computed by the company in USD terms.
A33: C. Capital expenditure and asset intensity
A34: C01 | B34: Capital expenditure | C34: ='Raw Data'!C19 -> 2579 | D34: ='Raw Data'!D19 -> 2201 | E34: ='Raw Data'!E19 -> 2237 | F34: ₹ crore | G34: Reported | H34: Raw Data R14 | I34: Basis (cash paid vs additions) is not stated in the source.
A35: C02 | B35: Capex ÷ revenue | C35: =IFERROR(C34/'Raw Data'!C6,"n.a.") -> 0.01757207 | D35: =IFERROR(D34/'Raw Data'!D6,"n.a.") -> 0.0143229 | E35: =IFERROR(E34/'Raw Data'!E6,"n.a.") -> 0.013724768 | F35: % | G35: Calculated | H35: C01 ÷ Revenue | I35: Capital intensity.
A36: C03 | B36: Capex ÷ operating profit | C36: =IFERROR(C34/'Raw Data'!C7,"n.a.") -> 0.08344928 | D36: =IFERROR(D34/'Raw Data'!D7,"n.a.") -> 0.069329385 | E36: =IFERROR(E34/'Raw Data'!E7,"n.a.") -> 0.064983732 | F36: % | G36: Calculated | H36: C01 ÷ Operating profit
A37: C04 | B37: Capex ÷ PAT | C37: =IFERROR(C34/'Raw Data'!C11,"n.a.") -> 0.10697694 | D37: =IFERROR(D34/'Raw Data'!D11,"n.a.") -> 0.083854008 | E37: =IFERROR(E34/'Raw Data'!E11,"n.a.") -> 0.083626168 | F37: % | G37: Calculated | H37: C01 ÷ PAT
A38: C05 | B38: Property, plant and equipment + right-of-use assets | C38: ='Raw Data'!C17+'Raw Data'!C18 -> 20675 | D38: ='Raw Data'!D17+'Raw Data'!D18 -> 19370 | E38: ='Raw Data'!E17+'Raw Data'!E18 -> 19111 | F38: ₹ crore | G38: Calculated | H38: R12 + R13
A39: C06 | B39: (PPE + right-of-use) ÷ total assets | C39: =IFERROR(C38/'Raw Data'!C23,"n.a.") -> 0.16432727 | D39: =IFERROR(D38/'Raw Data'!D23,"n.a.") -> 0.14055176 | E39: =IFERROR(E38/'Raw Data'!E23,"n.a.") -> 0.1283453 | F39: % | G39: Calculated | H39: C05 ÷ Total assets | I39: Falling share = asset base is becoming more financial and less physical.
A40: D. Profitability cross-checks (calculated vs printed) and reported returns
A41: D01 | B41: Operating margin (calculated) | C41: =IFERROR('Raw Data'!C7/'Raw Data'!C6,"n.a.") -> 0.21057186 | D41: =IFERROR('Raw Data'!D7/'Raw Data'!D6,"n.a.") -> 0.20659205 | E41: =IFERROR('Raw Data'!E7/'Raw Data'!E6,"n.a.") -> 0.21120314 | F41: % | G41: Calculated | H41: Operating profit ÷ Revenue
A42: D02 | B42: Operating margin (printed) | C42: ='Raw Data'!C30 -> 0.211 | D42: ='Raw Data'!D30 -> 0.207 | E42: ='Raw Data'!E30 -> 0.211 | F42: % | G42: Reported ratio | H42: Raw Data Q05
A43: D03 | B43: PAT margin (calculated) | C43: =IFERROR('Raw Data'!C11/'Raw Data'!C6,"n.a.") -> 0.16426036 | D43: =IFERROR('Raw Data'!D11/'Raw Data'!D6,"n.a.") -> 0.17080757 | E43: =IFERROR('Raw Data'!E11/'Raw Data'!E6,"n.a.") -> 0.1641205 | F43: % | G43: Calculated | H43: PAT ÷ Revenue
A44: D04 | B44: PAT margin (printed) | C44: ='Raw Data'!C35 -> 0.164 | D44: ='Raw Data'!D35 -> 0.171 | E44: ='Raw Data'!E35 -> 0.164 | F44: % | G44: Reported ratio | H44: Raw Data Q10
A45: D05 | B45: Effective tax rate (calculated) | C45: =IFERROR('Raw Data'!C10/'Raw Data'!C9,"n.a.") -> 0.27651401 | D45: =IFERROR('Raw Data'!D10/'Raw Data'!D9,"n.a.") -> 0.27064577 | E45: =IFERROR('Raw Data'!E10/'Raw Data'!E9,"n.a.") -> 0.28871517 | F45: % | G45: Calculated | H45: Provision for taxation ÷ PBT
A46: D06 | B46: Effective tax rate (printed) | C46: ='Raw Data'!C34 -> 0.277 | D46: ='Raw Data'!D34 -> 0.271 | E46: ='Raw Data'!E34 -> 0.289 | F46: % | G46: Reported ratio | H46: Raw Data Q09
A47: D07 | B47: Dividend payout (printed) | C47: ='Raw Data'!C37 -> 0.695 | D47: ='Raw Data'!D37 -> 0.8 | E47: ='Raw Data'!E37 -> 0.517 | F47: % | G47: Reported ratio | H47: Raw Data Q12 | I47: Rupee amount of dividends is not in the source.
A48: D08 | B48: Return on equity, USD terms (printed) | C48: ='Raw Data'!C36 -> 0.312 | D48: ='Raw Data'!D36 -> 0.321 | E48: ='Raw Data'!E36 -> 0.29 | F48: % | G48: Reported ratio | H48: Raw Data Q11
A49: E. Cash generation - DERIVED from the printed OCF ÷ revenue ratio (approximate; range shown)
A50: E01 | B50: Operating cash flow ÷ revenue (printed) | C50: ='Raw Data'!C26 -> 0.157 | D50: ='Raw Data'!D26 -> 0.17 | E50: ='Raw Data'!E26 -> 0.226 | F50: % | G50: Reported ratio | H50: Raw Data Q01 | I50: The only cash-flow information in the source.
A51: E02 | B51: Operating cash flow - central estimate | C51: =C50*'Raw Data'!C6 -> 23042.419 | D51: =D50*'Raw Data'!D6 -> 26123.9 | E51: =E50*'Raw Data'!E6 -> 36835.74 | F51: ₹ crore | G51: DERIVED - approx. | H51: E01 × Revenue (R01) | I51: Not a reported figure. Rounding of the printed ratio means the true value is within the range in E03-E04.
A52: E03 | B52: Operating cash flow - low end of range | C52: =(C50-$C$6)*'Raw Data'!C6 -> 22969.036 | D52: =(D50-$C$6)*'Raw Data'!D6 -> 26047.065 | E52: =(E50-$C$6)*'Raw Data'!E6 -> 36754.245 | F52: ₹ crore | G52: DERIVED - approx. | H52: (E01 − AS1) × Revenue
A53: E04 | B53: Operating cash flow - high end of range | C53: =(C50+$C$6)*'Raw Data'!C6 -> 23115.803 | D53: =(D50+$C$6)*'Raw Data'!D6 -> 26200.735 | E53: =(E50+$C$6)*'Raw Data'!E6 -> 36917.235 | F53: ₹ crore | G53: DERIVED - approx. | H53: (E01 + AS1) × Revenue
A54: E05 | B54: Capital expenditure (from C01) | C54: =C34 -> 2579 | D54: =D34 -> 2201 | E54: =E34 -> 2237 | F54: ₹ crore | G54: Reported | H54: C01
A55: E06 | B55: Free cash flow - central estimate | C55: =C51-C54 -> 20463.419 | D55: =D51-D54 -> 23922.9 | E55: =E51-E54 -> 34598.74 | F55: ₹ crore | G55: DERIVED - approx. | H55: E02 − E05 | I55: FCF = operating cash flow − capex. Approximate because OCF is rebuilt from a rounded ratio and the capex basis is not stated.
A56: E07 | B56: Free cash flow - low end of range | C56: =C52-C54 -> 20390.036 | D56: =D52-D54 -> 23846.065 | E56: =E52-E54 -> 34517.245 | F56: ₹ crore | G56: DERIVED - approx. | H56: E03 − E05
A57: E08 | B57: Free cash flow - high end of range | C57: =C53-C54 -> 20536.803 | D57: =D53-D54 -> 23999.735 | E57: =E53-E54 -> 34680.235 | F57: ₹ crore | G57: DERIVED - approx. | H57: E04 − E05
A58: E09 | B58: Free cash flow margin (FCF ÷ revenue) | C58: =IFERROR(C55/'Raw Data'!C6,"n.a.") -> 0.13942793 | D58: =IFERROR(D55/'Raw Data'!D6,"n.a.") -> 0.1556771 | E58: =IFERROR(E55/'Raw Data'!E6,"n.a.") -> 0.21227523 | F58: % | G58: DERIVED - approx. | H58: E06 ÷ Revenue
A59: E10 | B59: Cash conversion: OCF ÷ PAT - central | C59: =IFERROR(C51/'Raw Data'!C11,"n.a.") -> 0.95579969 | D59: =IFERROR(D51/'Raw Data'!D11,"n.a.") -> 0.99527202 | E59: =IFERROR(E51/'Raw Data'!E11,"n.a.") -> 1.377037 | F59: x | G59: DERIVED - approx. | H59: E02 ÷ PAT (R06) | I59: Above 1.0x means operating cash flow exceeded accounting profit.
A60: E11 | B60: Cash conversion: OCF ÷ PAT - low | C60: =IFERROR(C52/'Raw Data'!C11,"n.a.") -> 0.95275574 | D60: =IFERROR(D52/'Raw Data'!D11,"n.a.") -> 0.99234475 | E60: =IFERROR(E52/'Raw Data'!E11,"n.a.") -> 1.3739905 | F60: x | G60: DERIVED - approx. | H60: E03 ÷ PAT
A61: E12 | B61: Cash conversion: OCF ÷ PAT - high | C61: =IFERROR(C53/'Raw Data'!C11,"n.a.") -> 0.95884364 | D61: =IFERROR(D53/'Raw Data'!D11,"n.a.") -> 0.99819929 | E61: =IFERROR(E53/'Raw Data'!E11,"n.a.") -> 1.3800836 | F61: x | G61: DERIVED - approx. | H61: E04 ÷ PAT
A62: E13 | B62: FCF ÷ PAT - central | C62: =IFERROR(C55/'Raw Data'!C11,"n.a.") -> 0.84882276 | D62: =IFERROR(D55/'Raw Data'!D11,"n.a.") -> 0.91141801 | E62: =IFERROR(E55/'Raw Data'!E11,"n.a.") -> 1.2934108 | F62: x | G62: DERIVED - approx. | H62: E06 ÷ PAT
A63: E14 | B63: Change in cash + investments during the year | C63: n.a. | D63: =D11-C11 -> 7758 | E63: =E11-D11 -> 8587 | F63: ₹ crore | G63: Calculated | H63: A03 this year − A03 last year | I63: Can also move for reasons other than cash flow (e.g. fair-value and currency effects).
A64: E15 | B64: Residual: FCF not reflected in the rise in cash + investments | C64: n.a. | D64: =D55-D63 -> 16164.9 | E64: =E55-E63 -> 26011.74 | F64: ₹ crore | G64: DERIVED - approx. | H64: E06 − E14 | I64: Cash that left the pool for reasons the source does not itemise (it cannot say whether dividends, leases, acquisitions or other items). Indicative only; not a cash bridge.
A65: E16 | B65: Residual as % of FCF | C65: n.a. | D65: =IFERROR(D64/D55,"n.a.") -> 0.67570821 | E65: =IFERROR(E64/E55,"n.a.") -> 0.75181177 | F65: % | G65: DERIVED - approx. | H65: E15 ÷ E06
A66: E17 | B66: Company 'cash and investments' rebuilt from ratio × total assets | C66: ='Raw Data'!C27*'Raw Data'!C23 -> 31328.184 | D66: ='Raw Data'!D27*'Raw Data'!D23 -> 39001.362 | E66: ='Raw Data'!E27*'Raw Data'!E23 -> 47500.057 | F66: ₹ crore | G66: DERIVED - approx. | H66: Q02 × Total assets | I66: Used only as a consistency test of the printed ratios.
A67: E18 | B67: Company 'cash and investments' rebuilt from ratio × revenue | C67: ='Raw Data'!C28*'Raw Data'!C6 -> 31261.371 | D67: ='Raw Data'!D28*'Raw Data'!D6 -> 39032.18 | E67: ='Raw Data'!E28*'Raw Data'!E6 -> 47593.08 | F67: ₹ crore | G67: DERIVED - approx. | H67: Q03 × Revenue
A68: E19 | B68: Difference between the two rebuilds | C68: =C67-C66 -> -66.813 | D68: =D67-D66 -> 30.818 | E68: =E67-E66 -> 93.023 | F68: ₹ crore | G68: Check | H68: E18 − E17 | I68: Should be within the combined rounding tolerance of the two ratios.
A69: F. NOT AVAILABLE in this source (flagged - never estimated silently)
B70: Item | C70: Status | G70: Where it would come from | H70: What the PDF has instead | I70: Treatment in this model
A71: N01 | B71: Net cash from operating activities (Rs crore) | C71: Not available in source | G71: Cash flow statement | H71: Only the ratio 'Operating cash flows / revenue' (p.1) is printed. | I71: Approximated in the model from the rounded ratio and labelled DERIVED with a rounding range.
A72: N02 | B72: Free cash flow (reported) | C72: Not available in source | G72: Cash flow statement / results release | H72: Not in the file. | I72: Approximated as derived OCF minus the file's capital expenditure, with range.
A73: N03 | B73: Total current assets | C73: Not available in source | G73: Balance sheet | H73: Not in the file (only 'net current assets'). | I73: Current ratio NOT calculated.
A74: N04 | B74: Total current liabilities | C74: Not available in source | G74: Balance sheet | H74: Not in the file. | I74: Current ratio, cash ratio, expanded cash coverage and OCF ratio NOT calculated.
A75: N05 | B75: Unearned revenue, trade payables and other current liability lines | C75: Not available in source | G75: Balance sheet and notes | H75: Not in the file. | I75: Cannot analyse what drives short-term obligations.
A76: N06 | B76: Split of investments between current and non-current | C76: Not available in source | G76: Balance sheet / investment note | H76: Combined line only. | I76: Cash + investments is a broad measure, not a current-asset measure.
A77: N07 | B77: Dividends paid, buy-backs, lease payments, tax paid (Rs crore) | C77: Not available in source | G77: Cash flow statement | H77: Only the dividend payout ratio is printed. | I77: Uses of cash cannot be itemised; only an unexplained residual is shown.
A78: N08 | B78: Interest received / treasury income | C78: Not available in source | G78: Notes | H78: Only 'other income / revenue' is printed. | I78: Treasury yield on cash and investments NOT calculated.
A79: N09 | B79: Capital commitments, contingent liabilities, credit lines | C79: Not available in source | G79: Notes to the financial statements | H79: Not in the file. | I79: Forward-looking cash calls not assessed.
A80: N10 | B80: Daily or intra-year cash balances and management forecasts | C80: Not available in source | G80: Internal treasury data | H80: Never published in annual reports. | I80: Out of scope for any public-data analysis.

Sheet Trend Analysis
A1: Trend Analysis
A2: Year-on-year change, two-year compound growth and a formula-driven reading of each direction. Rows marked DERIVED are approximate (see Financial Calculations, Part E).
A4: Part 1 - Rupee amounts (₹ crore): growth rates
A5: Ref | B5: Metric | C5: FY23 | D5: FY24 | E5: FY25 | F5: YoY FY24 | G5: YoY FY25 | H5: 2-yr CAGR | I5: Pattern | J5: Higher is | K5: Two-year signal | L5: Basis
A6: T01 | B6: Revenue | C6: ='Raw Data'!C6 -> 146767 | D6: ='Raw Data'!D6 -> 153670 | E6: ='Raw Data'!E6 -> 162990 | F6: =IFERROR(D6/C6-1,"n.m.") -> 0.047033734 | G6: =IFERROR(E6/D6-1,"n.m.") -> 0.060649444 | H6: =IFERROR((E6/C6)^(1/2)-1,"n.m.") -> 0.053819599 | I6: =IF(AND(D6>C6,E6>D6),"Rose in both years",IF(AND(D6<C6,E6<D6),"Fell in both years",IF(AND(D6>=C6,E6<D6),"Rose, then fell",IF(AND(D6<C6,E6>=D6),"Fell, then rose","Flat")))) -> Rose in both years | J6: Better | K6: =IF(J6="Neutral","–",IF(E6=C6,"Unchanged",IF(SIGN(E6-C6)*IF(J6="Better",1,-1)>0,"Favourable","Unfavourable"))) -> Favourable | L6: Reported
A7: T02 | B7: Operating profit | C7: ='Raw Data'!C7 -> 30905 | D7: ='Raw Data'!D7 -> 31747 | E7: ='Raw Data'!E7 -> 34424 | F7: =IFERROR(D7/C7-1,"n.m.") -> 0.027244782 | G7: =IFERROR(E7/D7-1,"n.m.") -> 0.084322928 | H7: =IFERROR((E7/C7)^(1/2)-1,"n.m.") -> 0.055398063 | I7: =IF(AND(D7>C7,E7>D7),"Rose in both years",IF(AND(D7<C7,E7<D7),"Fell in both years",IF(AND(D7>=C7,E7<D7),"Rose, then fell",IF(AND(D7<C7,E7>=D7),"Fell, then rose","Flat")))) -> Rose in both years | J7: Better | K7: =IF(J7="Neutral","–",IF(E7=C7,"Unchanged",IF(SIGN(E7-C7)*IF(J7="Better",1,-1)>0,"Favourable","Unfavourable"))) -> Favourable | L7: Reported
A8: T03 | B8: Profit after tax | C8: ='Raw Data'!C11 -> 24108 | D8: ='Raw Data'!D11 -> 26248 | E8: ='Raw Data'!E11 -> 26750 | F8: =IFERROR(D8/C8-1,"n.m.") -> 0.088767214 | G8: =IFERROR(E8/D8-1,"n.m.") -> 0.019125267 | H8: =IFERROR((E8/C8)^(1/2)-1,"n.m.") -> 0.053370864 | I8: =IF(AND(D8>C8,E8>D8),"Rose in both years",IF(AND(D8<C8,E8<D8),"Fell in both years",IF(AND(D8>=C8,E8<D8),"Rose, then fell",IF(AND(D8<C8,E8>=D8),"Fell, then rose","Flat")))) -> Rose in both years | J8: Better | K8: =IF(J8="Neutral","–",IF(E8=C8,"Unchanged",IF(SIGN(E8-C8)*IF(J8="Better",1,-1)>0,"Favourable","Unfavourable"))) -> Favourable | L8: Reported
A9: T04 | B9: Equity | C9: ='Raw Data'!C15 -> 75795 | D9: ='Raw Data'!D15 -> 88461 | E9: ='Raw Data'!E15 -> 96203 | F9: =IFERROR(D9/C9-1,"n.m.") -> 0.16710865 | G9: =IFERROR(E9/D9-1,"n.m.") -> 0.087518794 | H9: =IFERROR((E9/C9)^(1/2)-1,"n.m.") -> 0.12661111 | I9: =IF(AND(D9>C9,E9>D9),"Rose in both years",IF(AND(D9<C9,E9<D9),"Fell in both years",IF(AND(D9>=C9,E9<D9),"Rose, then fell",IF(AND(D9<C9,E9>=D9),"Fell, then rose","Flat")))) -> Rose in both years | J9: Better | K9: =IF(J9="Neutral","–",IF(E9=C9,"Unchanged",IF(SIGN(E9-C9)*IF(J9="Better",1,-1)>0,"Favourable","Unfavourable"))) -> Favourable | L9: Reported
A10: T05 | B10: Total assets | C10: ='Raw Data'!C23 -> 125816 | D10: ='Raw Data'!D23 -> 137814 | E10: ='Raw Data'!E23 -> 148903 | F10: =IFERROR(D10/C10-1,"n.m.") -> 0.09536148 | G10: =IFERROR(E10/D10-1,"n.m.") -> 0.080463523 | H10: =IFERROR((E10/C10)^(1/2)-1,"n.m.") -> 0.087887 | I10: =IF(AND(D10>C10,E10>D10),"Rose in both years",IF(AND(D10<C10,E10<D10),"Fell in both years",IF(AND(D10>=C10,E10<D10),"Rose, then fell",IF(AND(D10<C10,E10>=D10),"Fell, then rose","Flat")))) -> Rose in both years | J10: Neutral | K10: =IF(J10="Neutral","–",IF(E10=C10,"Unchanged",IF(SIGN(E10-C10)*IF(J10="Better",1,-1)>0,"Favourable","Unfavourable"))) -> – | L10: Reported
A11: T06 | B11: Cash and cash equivalents | C11: ='Financial Calculations'!C9 -> 12173 | D11: ='Financial Calculations'!D9 -> 14786 | E11: ='Financial Calculations'!E9 -> 24455 | F11: =IFERROR(D11/C11-1,"n.m.") -> 0.21465538 | G11: =IFERROR(E11/D11-1,"n.m.") -> 0.65392939 | H11: =IFERROR((E11/C11)^(1/2)-1,"n.m.") -> 0.41737583 | I11: =IF(AND(D11>C11,E11>D11),"Rose in both years",IF(AND(D11<C11,E11<D11),"Fell in both years",IF(AND(D11>=C11,E11<D11),"Rose, then fell",IF(AND(D11<C11,E11>=D11),"Fell, then rose","Flat")))) -> Rose in both years | J11: Better | K11: =IF(J11="Neutral","–",IF(E11=C11,"Unchanged",IF(SIGN(E11-C11)*IF(J11="Better",1,-1)>0,"Favourable","Unfavourable"))) -> Favourable | L11: Reported
A12: T07 | B12: Investments (current + non-current) | C12: ='Financial Calculations'!C10 -> 19478 | D12: ='Financial Calculations'!D10 -> 24623 | E12: ='Financial Calculations'!E10 -> 23541 | F12: =IFERROR(D12/C12-1,"n.m.") -> 0.26414416 | G12: =IFERROR(E12/D12-1,"n.m.") -> -0.043942655 | H12: =IFERROR((E12/C12)^(1/2)-1,"n.m.") -> 0.099360865 | I12: =IF(AND(D12>C12,E12>D12),"Rose in both years",IF(AND(D12<C12,E12<D12),"Fell in both years",IF(AND(D12>=C12,E12<D12),"Rose, then fell",IF(AND(D12<C12,E12>=D12),"Fell, then rose","Flat")))) -> Rose, then fell | J12: Neutral | K12: =IF(J12="Neutral","–",IF(E12=C12,"Unchanged",IF(SIGN(E12-C12)*IF(J12="Better",1,-1)>0,"Favourable","Unfavourable"))) -> – | L12: Reported
A13: T08 | B13: Cash + investments | C13: ='Financial Calculations'!C11 -> 31651 | D13: ='Financial Calculations'!D11 -> 39409 | E13: ='Financial Calculations'!E11 -> 47996 | F13: =IFERROR(D13/C13-1,"n.m.") -> 0.24511074 | G13: =IFERROR(E13/D13-1,"n.m.") -> 0.21789439 | H13: =IFERROR((E13/C13)^(1/2)-1,"n.m.") -> 0.23142738 | I13: =IF(AND(D13>C13,E13>D13),"Rose in both years",IF(AND(D13<C13,E13<D13),"Fell in both years",IF(AND(D13>=C13,E13<D13),"Rose, then fell",IF(AND(D13<C13,E13>=D13),"Fell, then rose","Flat")))) -> Rose in both years | J13: Better | K13: =IF(J13="Neutral","–",IF(E13=C13,"Unchanged",IF(SIGN(E13-C13)*IF(J13="Better",1,-1)>0,"Favourable","Unfavourable"))) -> Favourable | L13: Calculated
A14: T09 | B14: Net current assets | C14: ='Financial Calculations'!C21 -> 31695 | D14: ='Financial Calculations'!D21 -> 50638 | E14: ='Financial Calculations'!E21 -> 54249 | F14: =IFERROR(D14/C14-1,"n.m.") -> 0.59766525 | G14: =IFERROR(E14/D14-1,"n.m.") -> 0.071310083 | H14: =IFERROR((E14/C14)^(1/2)-1,"n.m.") -> 0.30827936 | I14: =IF(AND(D14>C14,E14>D14),"Rose in both years",IF(AND(D14<C14,E14<D14),"Fell in both years",IF(AND(D14>=C14,E14<D14),"Rose, then fell",IF(AND(D14<C14,E14>=D14),"Fell, then rose","Flat")))) -> Rose in both years | J14: Better | K14: =IF(J14="Neutral","–",IF(E14=C14,"Unchanged",IF(SIGN(E14-C14)*IF(J14="Better",1,-1)>0,"Favourable","Unfavourable"))) -> Favourable | L14: Reported
A15: T10 | B15: Capital expenditure | C15: ='Financial Calculations'!C34 -> 2579 | D15: ='Financial Calculations'!D34 -> 2201 | E15: ='Financial Calculations'!E34 -> 2237 | F15: =IFERROR(D15/C15-1,"n.m.") -> -0.14656844 | G15: =IFERROR(E15/D15-1,"n.m.") -> 0.016356202 | H15: =IFERROR((E15/C15)^(1/2)-1,"n.m.") -> -0.068662005 | I15: =IF(AND(D15>C15,E15>D15),"Rose in both years",IF(AND(D15<C15,E15<D15),"Fell in both years",IF(AND(D15>=C15,E15<D15),"Rose, then fell",IF(AND(D15<C15,E15>=D15),"Fell, then rose","Flat")))) -> Fell, then rose | J15: Neutral | K15: =IF(J15="Neutral","–",IF(E15=C15,"Unchanged",IF(SIGN(E15-C15)*IF(J15="Better",1,-1)>0,"Favourable","Unfavourable"))) -> – | L15: Reported
A16: T11 | B16: Finance cost | C16: ='Financial Calculations'!C26 -> 284 | D16: ='Financial Calculations'!D26 -> 470 | E16: ='Financial Calculations'!E26 -> 416 | F16: =IFERROR(D16/C16-1,"n.m.") -> 0.65492958 | G16: =IFERROR(E16/D16-1,"n.m.") -> -0.11489362 | H16: =IFERROR((E16/C16)^(1/2)-1,"n.m.") -> 0.21028457 | I16: =IF(AND(D16>C16,E16>D16),"Rose in both years",IF(AND(D16<C16,E16<D16),"Fell in both years",IF(AND(D16>=C16,E16<D16),"Rose, then fell",IF(AND(D16<C16,E16>=D16),"Fell, then rose","Flat")))) -> Rose, then fell | J16: Worse | K16: =IF(J16="Neutral","–",IF(E16=C16,"Unchanged",IF(SIGN(E16-C16)*IF(J16="Better",1,-1)>0,"Favourable","Unfavourable"))) -> Unfavourable | L16: Reported
A17: T12 | B17: Operating cash flow - central | C17: ='Financial Calculations'!C51 -> 23042.419 | D17: ='Financial Calculations'!D51 -> 26123.9 | E17: ='Financial Calculations'!E51 -> 36835.74 | F17: =IFERROR(D17/C17-1,"n.m.") -> 0.13373079 | G17: =IFERROR(E17/D17-1,"n.m.") -> 0.41003985 | H17: =IFERROR((E17/C17)^(1/2)-1,"n.m.") -> 0.26435976 | I17: =IF(AND(D17>C17,E17>D17),"Rose in both years",IF(AND(D17<C17,E17<D17),"Fell in both years",IF(AND(D17>=C17,E17<D17),"Rose, then fell",IF(AND(D17<C17,E17>=D17),"Fell, then rose","Flat")))) -> Rose in both years | J17: Better | K17: =IF(J17="Neutral","–",IF(E17=C17,"Unchanged",IF(SIGN(E17-C17)*IF(J17="Better",1,-1)>0,"Favourable","Unfavourable"))) -> Favourable | L17: DERIVED - approx.
A18: T13 | B18: Free cash flow - central | C18: ='Financial Calculations'!C55 -> 20463.419 | D18: ='Financial Calculations'!D55 -> 23922.9 | E18: ='Financial Calculations'!E55 -> 34598.74 | F18: =IFERROR(D18/C18-1,"n.m.") -> 0.16905684 | G18: =IFERROR(E18/D18-1,"n.m.") -> 0.44626028 | H18: =IFERROR((E18/C18)^(1/2)-1,"n.m.") -> 0.30029246 | I18: =IF(AND(D18>C18,E18>D18),"Rose in both years",IF(AND(D18<C18,E18<D18),"Fell in both years",IF(AND(D18>=C18,E18<D18),"Rose, then fell",IF(AND(D18<C18,E18>=D18),"Fell, then rose","Flat")))) -> Rose in both years | J18: Better | K18: =IF(J18="Neutral","–",IF(E18=C18,"Unchanged",IF(SIGN(E18-C18)*IF(J18="Better",1,-1)>0,"Favourable","Unfavourable"))) -> Favourable | L18: DERIVED - approx.
A20: Part 2 - Ratios: change in percentage points (pp), days or times
A21: Ref | B21: Metric | C21: FY23 | D21: FY24 | E21: FY25 | F21: Δ FY24 | G21: Δ FY25 | H21: Δ FY23→FY25 | I21: Pattern | J21: Higher is | K21: Two-year signal | L21: Basis
A22: T14 | B22: Operating cash flow ÷ revenue (printed) | C22: ='Financial Calculations'!C50 -> 0.157 | D22: ='Financial Calculations'!D50 -> 0.17 | E22: ='Financial Calculations'!E50 -> 0.226 | F22: =(D22-C22)*100 -> 1.3 | G22: =(E22-D22)*100 -> 5.6 | H22: =(E22-C22)*100 -> 6.9 | I22: =IF(AND(D22>C22,E22>D22),"Rose in both years",IF(AND(D22<C22,E22<D22),"Fell in both years",IF(AND(D22>=C22,E22<D22),"Rose, then fell",IF(AND(D22<C22,E22>=D22),"Fell, then rose","Flat")))) -> Rose in both years | J22: Better | K22: =IF(J22="Neutral","–",IF(E22=C22,"Unchanged",IF(SIGN(E22-C22)*IF(J22="Better",1,-1)>0,"Favourable","Unfavourable"))) -> Favourable | L22: Reported ratio
A23: T15 | B23: Free cash flow margin | C23: ='Financial Calculations'!C58 -> 0.13942793 | D23: ='Financial Calculations'!D58 -> 0.1556771 | E23: ='Financial Calculations'!E58 -> 0.21227523 | F23: =(D23-C23)*100 -> 1.624917 | G23: =(E23-D23)*100 -> 5.6598131 | H23: =(E23-C23)*100 -> 7.2847302 | I23: =IF(AND(D23>C23,E23>D23),"Rose in both years",IF(AND(D23<C23,E23<D23),"Fell in both years",IF(AND(D23>=C23,E23<D23),"Rose, then fell",IF(AND(D23<C23,E23>=D23),"Fell, then rose","Flat")))) -> Rose in both years | J23: Better | K23: =IF(J23="Neutral","–",IF(E23=C23,"Unchanged",IF(SIGN(E23-C23)*IF(J23="Better",1,-1)>0,"Favourable","Unfavourable"))) -> Favourable | L23: DERIVED - approx.
A24: T16 | B24: Cash conversion: OCF ÷ PAT | C24: ='Financial Calculations'!C59 -> 0.95579969 | D24: ='Financial Calculations'!D59 -> 0.99527202 | E24: ='Financial Calculations'!E59 -> 1.377037 | F24: =(D24-C24) -> 0.039472328 | G24: =(E24-D24) -> 0.38176499 | H24: =(E24-C24) -> 0.42123732 | I24: =IF(AND(D24>C24,E24>D24),"Rose in both years",IF(AND(D24<C24,E24<D24),"Fell in both years",IF(AND(D24>=C24,E24<D24),"Rose, then fell",IF(AND(D24<C24,E24>=D24),"Fell, then rose","Flat")))) -> Rose in both years | J24: Better | K24: =IF(J24="Neutral","–",IF(E24=C24,"Unchanged",IF(SIGN(E24-C24)*IF(J24="Better",1,-1)>0,"Favourable","Unfavourable"))) -> Favourable | L24: DERIVED - approx.
A25: T17 | B25: Cash and investments ÷ total assets (company) | C25: ='Financial Calculations'!C15 -> 0.249 | D25: ='Financial Calculations'!D15 -> 0.283 | E25: ='Financial Calculations'!E15 -> 0.319 | F25: =(D25-C25)*100 -> 3.4 | G25: =(E25-D25)*100 -> 3.6 | H25: =(E25-C25)*100 -> 7 | I25: =IF(AND(D25>C25,E25>D25),"Rose in both years",IF(AND(D25<C25,E25<D25),"Fell in both years",IF(AND(D25>=C25,E25<D25),"Rose, then fell",IF(AND(D25<C25,E25>=D25),"Fell, then rose","Flat")))) -> Rose in both years | J25: Better | K25: =IF(J25="Neutral","–",IF(E25=C25,"Unchanged",IF(SIGN(E25-C25)*IF(J25="Better",1,-1)>0,"Favourable","Unfavourable"))) -> Favourable | L25: Reported ratio
A26: T18 | B26: Cash and investments ÷ revenue (company) | C26: ='Financial Calculations'!C18 -> 0.213 | D26: ='Financial Calculations'!D18 -> 0.254 | E26: ='Financial Calculations'!E18 -> 0.292 | F26: =(D26-C26)*100 -> 4.1 | G26: =(E26-D26)*100 -> 3.8 | H26: =(E26-C26)*100 -> 7.9 | I26: =IF(AND(D26>C26,E26>D26),"Rose in both years",IF(AND(D26<C26,E26<D26),"Fell in both years",IF(AND(D26>=C26,E26<D26),"Rose, then fell",IF(AND(D26<C26,E26>=D26),"Fell, then rose","Flat")))) -> Rose in both years | J26: Better | K26: =IF(J26="Neutral","–",IF(E26=C26,"Unchanged",IF(SIGN(E26-C26)*IF(J26="Better",1,-1)>0,"Favourable","Unfavourable"))) -> Favourable | L26: Reported ratio
A27: T19 | B27: Cash and equivalents ÷ (cash + investments) | C27: ='Financial Calculations'!C13 -> 0.3846008 | D27: ='Financial Calculations'!D13 -> 0.37519348 | E27: ='Financial Calculations'!E13 -> 0.50952163 | F27: =(D27-C27)*100 -> -0.94073188 | G27: =(E27-D27)*100 -> 13.432814 | H27: =(E27-C27)*100 -> 12.492082 | I27: =IF(AND(D27>C27,E27>D27),"Rose in both years",IF(AND(D27<C27,E27<D27),"Fell in both years",IF(AND(D27>=C27,E27<D27),"Rose, then fell",IF(AND(D27<C27,E27>=D27),"Fell, then rose","Flat")))) -> Fell, then rose | J27: Better | K27: =IF(J27="Neutral","–",IF(E27=C27,"Unchanged",IF(SIGN(E27-C27)*IF(J27="Better",1,-1)>0,"Favourable","Unfavourable"))) -> Favourable | L27: Calculated
A28: T20 | B28: Days of operating costs covered by cash + investments | C28: ='Financial Calculations'!C30 -> 99.710129 | D28: ='Financial Calculations'!D30 -> 117.97844 | E28: ='Financial Calculations'!E30 -> 136.26106 | F28: =(D28-C28) -> 18.268308 | G28: =(E28-D28) -> 18.282627 | H28: =(E28-C28) -> 36.550935 | I28: =IF(AND(D28>C28,E28>D28),"Rose in both years",IF(AND(D28<C28,E28<D28),"Fell in both years",IF(AND(D28>=C28,E28<D28),"Rose, then fell",IF(AND(D28<C28,E28>=D28),"Fell, then rose","Flat")))) -> Rose in both years | J28: Better | K28: =IF(J28="Neutral","–",IF(E28=C28,"Unchanged",IF(SIGN(E28-C28)*IF(J28="Better",1,-1)>0,"Favourable","Unfavourable"))) -> Favourable | L28: Calculated
A29: T21 | B29: Net current assets ÷ revenue | C29: ='Financial Calculations'!C22 -> 0.21595454 | D29: ='Financial Calculations'!D22 -> 0.32952431 | E29: ='Financial Calculations'!E22 -> 0.33283637 | F29: =(D29-C29)*100 -> 11.356977 | G29: =(E29-D29)*100 -> 0.3312065 | H29: =(E29-C29)*100 -> 11.688183 | I29: =IF(AND(D29>C29,E29>D29),"Rose in both years",IF(AND(D29<C29,E29<D29),"Fell in both years",IF(AND(D29>=C29,E29<D29),"Rose, then fell",IF(AND(D29<C29,E29>=D29),"Fell, then rose","Flat")))) -> Rose in both years | J29: Better | K29: =IF(J29="Neutral","–",IF(E29=C29,"Unchanged",IF(SIGN(E29-C29)*IF(J29="Better",1,-1)>0,"Favourable","Unfavourable"))) -> Favourable | L29: Calculated
A30: T22 | B30: Equity ÷ total assets | C30: ='Financial Calculations'!C24 -> 0.60242735 | D30: ='Financial Calculations'!D24 -> 0.64188689 | E30: ='Financial Calculations'!E24 -> 0.64607832 | F30: =(D30-C30)*100 -> 3.9459537 | G30: =(E30-D30)*100 -> 0.41914284 | H30: =(E30-C30)*100 -> 4.3650965 | I30: =IF(AND(D30>C30,E30>D30),"Rose in both years",IF(AND(D30<C30,E30<D30),"Fell in both years",IF(AND(D30>=C30,E30<D30),"Rose, then fell",IF(AND(D30<C30,E30>=D30),"Fell, then rose","Flat")))) -> Rose in both years | J30: Better | K30: =IF(J30="Neutral","–",IF(E30=C30,"Unchanged",IF(SIGN(E30-C30)*IF(J30="Better",1,-1)>0,"Favourable","Unfavourable"))) -> Favourable | L30: Calculated
A31: T23 | B31: Capex ÷ revenue | C31: ='Financial Calculations'!C35 -> 0.01757207 | D31: ='Financial Calculations'!D35 -> 0.0143229 | E31: ='Financial Calculations'!E35 -> 0.013724768 | F31: =(D31-C31)*100 -> -0.32491703 | G31: =(E31-D31)*100 -> -0.059813133 | H31: =(E31-C31)*100 -> -0.38473016 | I31: =IF(AND(D31>C31,E31>D31),"Rose in both years",IF(AND(D31<C31,E31<D31),"Fell in both years",IF(AND(D31>=C31,E31<D31),"Rose, then fell",IF(AND(D31<C31,E31>=D31),"Fell, then rose","Flat")))) -> Fell in both years | J31: Neutral | K31: =IF(J31="Neutral","–",IF(E31=C31,"Unchanged",IF(SIGN(E31-C31)*IF(J31="Better",1,-1)>0,"Favourable","Unfavourable"))) -> – | L31: Calculated
A32: T24 | B32: Operating profit ÷ finance cost | C32: ='Financial Calculations'!C27 -> 108.82042 | D32: ='Financial Calculations'!D27 -> 67.546809 | E32: ='Financial Calculations'!E27 -> 82.75 | F32: =(D32-C32) -> -41.273614 | G32: =(E32-D32) -> 15.203191 | H32: =(E32-C32) -> -26.070423 | I32: =IF(AND(D32>C32,E32>D32),"Rose in both years",IF(AND(D32<C32,E32<D32),"Fell in both years",IF(AND(D32>=C32,E32<D32),"Rose, then fell",IF(AND(D32<C32,E32>=D32),"Fell, then rose","Flat")))) -> Fell, then rose | J32: Better | K32: =IF(J32="Neutral","–",IF(E32=C32,"Unchanged",IF(SIGN(E32-C32)*IF(J32="Better",1,-1)>0,"Favourable","Unfavourable"))) -> Unfavourable | L32: Calculated
A33: T25 | B33: Day's sales outstanding (printed, USD terms) | C33: ='Financial Calculations'!C32 -> 62 | D33: ='Financial Calculations'!D32 -> 71 | E33: ='Financial Calculations'!E32 -> 69 | F33: =(D33-C33) -> 9 | G33: =(E33-D33) -> -2 | H33: =(E33-C33) -> 7 | I33: =IF(AND(D33>C33,E33>D33),"Rose in both years",IF(AND(D33<C33,E33<D33),"Fell in both years",IF(AND(D33>=C33,E33<D33),"Rose, then fell",IF(AND(D33<C33,E33>=D33),"Fell, then rose","Flat")))) -> Rose, then fell | J33: Worse | K33: =IF(J33="Neutral","–",IF(E33=C33,"Unchanged",IF(SIGN(E33-C33)*IF(J33="Better",1,-1)>0,"Favourable","Unfavourable"))) -> Unfavourable | L33: Reported ratio
A34: T26 | B34: Dividend payout (printed) | C34: ='Financial Calculations'!C47 -> 0.695 | D34: ='Financial Calculations'!D47 -> 0.8 | E34: ='Financial Calculations'!E47 -> 0.517 | F34: =(D34-C34)*100 -> 10.5 | G34: =(E34-D34)*100 -> -28.3 | H34: =(E34-C34)*100 -> -17.8 | I34: =IF(AND(D34>C34,E34>D34),"Rose in both years",IF(AND(D34<C34,E34<D34),"Fell in both years",IF(AND(D34>=C34,E34<D34),"Rose, then fell",IF(AND(D34<C34,E34>=D34),"Fell, then rose","Flat")))) -> Rose, then fell | J34: Neutral | K34: =IF(J34="Neutral","–",IF(E34=C34,"Unchanged",IF(SIGN(E34-C34)*IF(J34="Better",1,-1)>0,"Favourable","Unfavourable"))) -> – | L34: Reported ratio
A35: T27 | B35: Operating margin (printed) | C35: ='Financial Calculations'!C42 -> 0.211 | D35: ='Financial Calculations'!D42 -> 0.207 | E35: ='Financial Calculations'!E42 -> 0.211 | F35: =(D35-C35)*100 -> -0.4 | G35: =(E35-D35)*100 -> 0.4 | H35: =(E35-C35)*100 -> 0 | I35: =IF(AND(D35>C35,E35>D35),"Rose in both years",IF(AND(D35<C35,E35<D35),"Fell in both years",IF(AND(D35>=C35,E35<D35),"Rose, then fell",IF(AND(D35<C35,E35>=D35),"Fell, then rose","Flat")))) -> Fell, then rose | J35: Better | K35: =IF(J35="Neutral","–",IF(E35=C35,"Unchanged",IF(SIGN(E35-C35)*IF(J35="Better",1,-1)>0,"Favourable","Unfavourable"))) -> Unchanged | L35: Reported ratio
A36: T28 | B36: PAT margin (printed) | C36: ='Financial Calculations'!C44 -> 0.164 | D36: ='Financial Calculations'!D44 -> 0.171 | E36: ='Financial Calculations'!E44 -> 0.164 | F36: =(D36-C36)*100 -> 0.7 | G36: =(E36-D36)*100 -> -0.7 | H36: =(E36-C36)*100 -> 0 | I36: =IF(AND(D36>C36,E36>D36),"Rose in both years",IF(AND(D36<C36,E36<D36),"Fell in both years",IF(AND(D36>=C36,E36<D36),"Rose, then fell",IF(AND(D36<C36,E36>=D36),"Fell, then rose","Flat")))) -> Rose, then fell | J36: Better | K36: =IF(J36="Neutral","–",IF(E36=C36,"Unchanged",IF(SIGN(E36-C36)*IF(J36="Better",1,-1)>0,"Favourable","Unfavourable"))) -> Unchanged | L36: Reported ratio
A37: T29 | B37: Return on equity, USD terms (printed) | C37: ='Financial Calculations'!C48 -> 0.312 | D37: ='Financial Calculations'!D48 -> 0.321 | E37: ='Financial Calculations'!E48 -> 0.29 | F37: =(D37-C37)*100 -> 0.9 | G37: =(E37-D37)*100 -> -3.1 | H37: =(E37-C37)*100 -> -2.2 | I37: =IF(AND(D37>C37,E37>D37),"Rose in both years",IF(AND(D37<C37,E37<D37),"Fell in both years",IF(AND(D37>=C37,E37<D37),"Rose, then fell",IF(AND(D37<C37,E37>=D37),"Fell, then rose","Flat")))) -> Rose, then fell | J37: Better | K37: =IF(J37="Neutral","–",IF(E37=C37,"Unchanged",IF(SIGN(E37-C37)*IF(J37="Better",1,-1)>0,"Favourable","Unfavourable"))) -> Unfavourable | L37: Reported ratio
A39: Part 3 - Verdicts (formula-driven)
A40: # | B40: Question | C40: Verdict | F40: Evidence (live from the model)
A41: V1 | B41: Is operating cash generation improving? | C41: =IF(AND(E22>D22,D22>C22),"Improving",IF(AND(E22<D22,D22<C22),"Weakening","Mixed")) -> Improving | F41: ="OCF ÷ revenue (printed): "&TEXT(C22,"0.0%")&" → "&TEXT(D22,"0.0%")&" → "&TEXT(E22,"0.0%")&". Derived OCF about ₹"&TEXT(C17,"#,##0")&" → ₹"&TEXT(D17,"#,##0")&" → ₹"&TEXT(E17,"#,##0")&" crore (approximate)." -> OCF ÷ revenue (printed): 15.7% → 17.0% → 22.6%. Derived OCF about ₹23,042 → ₹26,124 → ₹36,836 crore (approximate).
A42: V2 | B42: Is free cash flow after capex improving? | C42: =IF(AND(E23>D23,D23>C23),"Improving",IF(AND(E23<D23,D23<C23),"Weakening","Mixed")) -> Improving | F42: ="Derived FCF margin: "&TEXT(C23,"0.0%")&" → "&TEXT(D23,"0.0%")&" → "&TEXT(E23,"0.0%")&"; derived FCF about ₹"&TEXT(E18,"#,##0")&" crore in FY25 (approximate)." -> Derived FCF margin: 13.9% → 15.6% → 21.2%; derived FCF about ₹34,599 crore in FY25 (approximate).
A43: V3 | B43: Is the cash + investments buffer growing relative to the balance sheet? | C43: =IF(AND(E25>D25,D25>C25),"Improving",IF(AND(E25<D25,D25<C25),"Weakening","Mixed")) -> Improving | F43: ="Cash and investments ÷ total assets (company): "&TEXT(C25,"0.0%")&" → "&TEXT(D25,"0.0%")&" → "&TEXT(E25,"0.0%")&"." -> Cash and investments ÷ total assets (company): 24.9% → 28.3% → 31.9%.
A44: V4 | B44: Does the buffer cover more days of operating costs? | C44: =IF(AND(E28>D28,D28>C28),"Improving",IF(AND(E28<D28,D28<C28),"Weakening","Mixed")) -> Improving | F44: ="Days covered by cash + investments: "&TEXT(C28,"0")&" → "&TEXT(D28,"0")&" → "&TEXT(E28,"0")&" (cash and equivalents alone: "&TEXT('Financial Calculations'!C31,"0")&" → "&TEXT('Financial Calculations'!E31,"0")&")." -> Days covered by cash + investments: 100 → 118 → 136 (cash and equivalents alone: 38 → 69).
A45: V5 | B45: Is the capex burden changing? (lower = lighter) | C45: =IF(AND(E31>D31,D31>C31),"Heavier",IF(AND(E31<D31,D31<C31),"Lighter","Mixed")) -> Lighter | F45: ="Capex ÷ revenue: "&TEXT(C31,"0.0%")&" → "&TEXT(D31,"0.0%")&" → "&TEXT(E31,"0.0%")&"." -> Capex ÷ revenue: 1.8% → 1.4% → 1.4%.
A46: V6 | B46: Does the company carry debt? | C46: =IF(SUM('Raw Data'!$C$16:$E$16)=0,"No debt","Debt present") -> No debt | F46: ="Debt shown as nil in all three years; finance cost still ₹"&TEXT('Raw Data'!C8,"#,##0")&", ₹"&TEXT('Raw Data'!D8,"#,##0")&" and ₹"&TEXT('Raw Data'!E8,"#,##0")&" crore (nature not stated in the source)." -> Debt shown as nil in all three years; finance cost still ₹284, ₹470 and ₹416 crore (nature not stated in the source).
A48: The verdicts compare FY23, FY24 and FY25 only. 'Mixed' means the metric did not move in the same direction in both years. Verdicts on DERIVED rows inherit the approximation.

Sheet Dashboard
B1: INFOSYS LIMITED — CASH FLOW & LIQUIDITY ANALYSIS
B2: FY2022-23 to FY2024-25 · ₹ crore · single source: Infosys 'Additional Information' (Annual Report 2024-25 extract). OCF and FCF are DERIVED approximations from a printed ratio; current/cash ratios are not available in this source.
B4: FY25 operating cash flow (derived, approx.) | E4: FY25 free cash flow (derived, approx.) | H4: FY25 cash + investments | K4: FY25 days of operating costs covered
B5: ='Financial Calculations'!E51 -> 36835.74 | E5: ='Financial Calculations'!E55 -> 34598.74 | H5: ='Financial Calculations'!E11 -> 47996 | K5: ='Financial Calculations'!E30 -> 136.26106
B6: ="Range ₹"&TEXT('Financial Calculations'!E52,"#,##0")&"–"&TEXT('Financial Calculations'!E53,"#,##0")&" cr (ratio "&TEXT('Financial Calculations'!E50,"0.0%")&" of revenue)" -> Range ₹36,754–36,917 cr (ratio 22.6% of revenue) | E6: ="OCF less capex of ₹"&TEXT('Financial Calculations'!E54,"#,##0")&" cr; margin "&TEXT('Financial Calculations'!E58,"0.0%") -> OCF less capex of ₹2,237 cr; margin 21.2% | H6: =TEXT('Financial Calculations'!E15,"0.0%")&" of total assets (company); debt nil" -> 31.9% of total assets (company); debt nil | K6: ="Cash alone: "&TEXT('Financial Calculations'!E31,"0")&" days; FY23: "&TEXT('Financial Calculations'!C30,"0")&" days" -> Cash alone: 69 days; FY23: 100 days
B7: Headline figures are linked to 'Financial Calculations' - nothing is typed twice. Orange-shaded numbers are derived approximations.
B9: Indicator | E9: FY23 | F9: FY24 | G9: FY25 | H9: Basis | O9: Chart data (links to the table at left) | P9: FY23 | Q9: FY24 | R9: FY25
B10: Cash and cash equivalents (₹ crore) | E10: ='Financial Calculations'!C9 -> 12173 | F10: ='Financial Calculations'!D9 -> 14786 | G10: ='Financial Calculations'!E9 -> 24455 | H10: Reported | O10: Cash and cash equivalents | P10: =E10 -> 12173 | Q10: =F10 -> 14786 | R10: =G10 -> 24455
B11: Investments, current + non-current (₹ crore) | E11: ='Financial Calculations'!C10 -> 19478 | F11: ='Financial Calculations'!D10 -> 24623 | G11: ='Financial Calculations'!E10 -> 23541 | H11: Reported | O11: Investments (current + non-current) | P11: =E11 -> 19478 | Q11: =F11 -> 24623 | R11: =G11 -> 23541
B12: Cash + investments (₹ crore) | E12: ='Financial Calculations'!C11 -> 31651 | F12: ='Financial Calculations'!D11 -> 39409 | G12: ='Financial Calculations'!E11 -> 47996 | H12: Calculated | O12: Operating cash flow (derived) | P12: =E13 -> 23042.419 | Q12: =F13 -> 26123.9 | R12: =G13 -> 36835.74
B13: Operating cash flow - central (₹ crore) | E13: ='Financial Calculations'!C51 -> 23042.419 | F13: ='Financial Calculations'!D51 -> 26123.9 | G13: ='Financial Calculations'!E51 -> 36835.74 | H13: DERIVED from printed OCF ÷ revenue (approx.) | O13: Capital expenditure | P13: =E14 -> 2579 | Q13: =F14 -> 2201 | R13: =G14 -> 2237
B14: Capital expenditure (₹ crore) | E14: ='Financial Calculations'!C34 -> 2579 | F14: ='Financial Calculations'!D34 -> 2201 | G14: ='Financial Calculations'!E34 -> 2237 | H14: Reported | O14: Free cash flow (derived) | P14: =E15 -> 20463.419 | Q14: =F15 -> 23922.9 | R14: =G15 -> 34598.74
B15: Free cash flow - central (₹ crore) | E15: ='Financial Calculations'!C55 -> 20463.419 | F15: ='Financial Calculations'!D55 -> 23922.9 | G15: ='Financial Calculations'!E55 -> 34598.74 | H15: DERIVED (approx.) | O15: Operating cash flow ÷ revenue | P15: =E16 -> 0.157 | Q15: =F16 -> 0.17 | R15: =G16 -> 0.226
B16: Operating cash flow ÷ revenue | E16: ='Financial Calculations'!C50 -> 0.157 | F16: ='Financial Calculations'!D50 -> 0.17 | G16: ='Financial Calculations'!E50 -> 0.226 | H16: Reported ratio | O16: Cash and investments ÷ total assets | P16: =E17 -> 0.249 | Q16: =F17 -> 0.283 | R16: =G17 -> 0.319
B17: Cash and investments ÷ total assets | E17: ='Financial Calculations'!C15 -> 0.249 | F17: ='Financial Calculations'!D15 -> 0.283 | G17: ='Financial Calculations'!E15 -> 0.319 | H17: Reported ratio (company) | O17: Cash and investments ÷ revenue | P17: =E18 -> 0.213 | Q17: =F18 -> 0.254 | R17: =G18 -> 0.292
B18: Cash and investments ÷ revenue | E18: ='Financial Calculations'!C18 -> 0.213 | F18: ='Financial Calculations'!D18 -> 0.254 | G18: ='Financial Calculations'!E18 -> 0.292 | H18: Reported ratio (company) | O18: Days of operating costs covered | P18: =E19 -> 99.710129 | Q18: =F19 -> 117.97844 | R18: =G19 -> 136.26106
B19: Days of operating costs covered by cash + investments | E19: ='Financial Calculations'!C30 -> 99.710129 | F19: ='Financial Calculations'!D30 -> 117.97844 | G19: ='Financial Calculations'!E30 -> 136.26106 | H19: Calculated | O19: Net current assets | P19: =E20 -> 31695 | Q19: =F20 -> 50638 | R19: =G20 -> 54249
B20: Net current assets (₹ crore) | E20: ='Financial Calculations'!C21 -> 31695 | F20: ='Financial Calculations'!D21 -> 50638 | G20: ='Financial Calculations'!E21 -> 54249 | H20: Reported
B22: Observations (text updates with the numbers) | O22: FCF vs rise in cash + investments (FY24-FY25) | P22: FY24 | Q22: FY25
B23: ="1. Cash generation "&IF('Financial Calculations'!E50>'Financial Calculations'!C50,"strengthened","weakened")&": operating cash flow ÷ revenue went "&TEXT('Financial Calculations'!C50,"0.0%")&" → "&TEXT('Financial Calculations'!D50,"0.0%")&" → "&TEXT('Financial Calculations'!E50,"0.0%")&" (derived OCF about ₹"&TEXT('Financial Calculations'!C51,"#,##0")&" → ₹"&TEXT('Financial Calculations'!E51,"#,##0")&" crore; rounding range about ±₹"&TEXT('Financial Calculations'!$C$6*'Raw Data'!E6,"#,##0")&" crore in FY25)." -> 1. Cash generation strengthened: operating cash flow ÷ revenue went 15.7% → 17.0% → 22.6% (derived OCF about ₹23,042 → ₹36,836 crore; rounding range about ±₹81 crore in FY25). | O23: Free cash flow (derived) | P23: ='Financial Calculations'!D55 -> 23922.9 | Q23: ='Financial Calculations'!E55 -> 34598.74
B24: ="2. Free cash flow (derived) was about ₹"&TEXT('Financial Calculations'!E55,"#,##0")&" crore in FY25 against ₹"&TEXT('Financial Calculations'!C55,"#,##0")&" crore in FY23; capex stayed small at "&TEXT('Financial Calculations'!E35,"0.0%")&" of revenue (FY23: "&TEXT('Financial Calculations'!C35,"0.0%")&")." -> 2. Free cash flow (derived) was about ₹34,599 crore in FY25 against ₹20,463 crore in FY23; capex stayed small at 1.4% of revenue (FY23: 1.8%). | O24: Rise in cash + investments | P24: ='Financial Calculations'!D63 -> 7758 | Q24: ='Financial Calculations'!E63 -> 8587
B25: ="3. The liquidity pool grew: cash + investments reached ₹"&TEXT('Financial Calculations'!E11,"#,##0")&" crore ("&TEXT('Financial Calculations'!E15,"0.0%")&" of total assets, up from "&TEXT('Financial Calculations'!C15,"0.0%")&"), covering about "&TEXT('Financial Calculations'!E30,"0")&" days of operating costs (FY23: "&TEXT('Financial Calculations'!C30,"0")&"). Debt is nil." -> 3. The liquidity pool grew: cash + investments reached ₹47,996 crore (31.9% of total assets, up from 24.9%), covering about 136 days of operating costs (FY23: 100). Debt is nil. | O25: Residual (not itemised in source) | P25: ='Financial Calculations'!D64 -> 16164.9 | Q25: ='Financial Calculations'!E64 -> 26011.74
B26: ="4. Composition shifted toward cash on hand: cash and equivalents were "&TEXT('Financial Calculations'!E13,"0%")&" of the pool in FY25 versus "&TEXT('Financial Calculations'!D13,"0%")&" in FY24, as investments edged down." -> 4. Composition shifted toward cash on hand: cash and equivalents were 51% of the pool in FY25 versus 38% in FY24, as investments edged down.
B27: ="5. Cash did not simply accumulate: derived FCF exceeded the rise in cash + investments by about ₹"&TEXT('Financial Calculations'!E64,"#,##0")&" crore in FY25 (FY24: ₹"&TEXT('Financial Calculations'!D64,"#,##0")&" crore). The source does not itemise where it went." -> 5. Cash did not simply accumulate: derived FCF exceeded the rise in cash + investments by about ₹26,012 crore in FY25 (FY24: ₹16,165 crore). The source does not itemise where it went.
B28: ="6. Limits: the source has no current assets, current liabilities or cash-flow statement in ₹, so the current ratio, cash ratio and OCF ratio are not calculated. OCF and FCF are approximations." -> 6. Limits: the source has no current assets, current liabilities or cash-flow statement in ₹, so the current ratio, cash ratio and OCF ratio are not calculated. OCF and FCF are approximations.
B78: Charts show three years only; DERIVED series are approximations and carry a rounding range (see Financial Calculations, Part E). Palette: blue / orange / green.

Sheet Data Sources and Audit Checks
A1: Data Sources and Audit Checks
A2: Part A: the one source document. Part B: formula-based integrity checks. Part C: limitations that apply to every result.
B4: OVERALL AUDIT STATUS | C4: =IF(COUNTIF(G14:G36,"CHECK")=0,"ALL PASS ("&COUNTIF(G14:G36,"PASS")&" checks)","REVIEW: "&COUNTIF(G14:G36,"CHECK")&" failing") -> ALL PASS (23 checks)
A6: Part A - Source register
A7: Code | B7: Document | C7: Pages | H7: What it provides to this model
A8: S1 | B8: Infosys Limited - Additional Information (extract of Annual Report 2024-25) - file: infosys.pdf | C8: 7 | H8: p.1 ratio analysis; p.2 charts of the same ratios; p.3 employee and revenue/PAT growth table; p.4 12-year Historical Data table; p.5-p.7 shareholder information (not used).
B9: Accounting basis: Ratio table (p.1) states: 'based on consolidated IFRS INR financial statements'. Revenue/PAT table (p.3) is headed IFRS (INR crore). The Historical Data table (p.4) is headed 'In Rs crore' and does not name the accounting basis.
B10: No other document, website or data provider was used for any number in this workbook. Official page for the report: infosys.com → Investors → Reports & filings (verify the PDF against it before citing).
A12: Part B - Integrity checks
A13: # | B13: Check | C13: FY23 | D13: FY24 | E13: FY25 | F13: Tolerance | G13: Result | H13: Why it matters
A14: 1 | B14: PBT − tax − PAT = 0 | C14: ='Raw Data'!C9-'Raw Data'!C10-'Raw Data'!C11 -> 0 | D14: ='Raw Data'!D9-'Raw Data'!D10-'Raw Data'!D11 -> 0 | E14: ='Raw Data'!E9-'Raw Data'!E10-'Raw Data'!E11 -> 0 | F14: 0.5 | G14: =IFERROR(IF(COUNT(C14:E14)<>3,"CHECK",IF(MAX(MAX(C14:E14),-MIN(C14:E14))<=F14,"PASS","CHECK")),"CHECK") -> PASS | H14: Income statement sub-totals agree.
A15: 2 | B15: PAT − (non-controlling + owners) = 0 | C15: ='Raw Data'!C11-'Raw Data'!C12-'Raw Data'!C13 -> 0 | D15: ='Raw Data'!D11-'Raw Data'!D12-'Raw Data'!D13 -> 0 | E15: ='Raw Data'!E11-'Raw Data'!E12-'Raw Data'!E13 -> 0 | F15: 0.5 | G15: =IFERROR(IF(COUNT(C15:E15)<>3,"CHECK",IF(MAX(MAX(C15:E15),-MIN(C15:E15))<=F15,"PASS","CHECK")),"CHECK") -> PASS | H15: Profit attribution adds up.
A16: 3 | B16: Revenue: p.4 table − p.3 table = 0 | C16: ='Raw Data'!C6-'Raw Data'!C48 -> 0 | D16: ='Raw Data'!D6-'Raw Data'!D48 -> 0 | E16: ='Raw Data'!E6-'Raw Data'!E48 -> 0 | F16: 0.5 | G16: =IFERROR(IF(COUNT(C16:E16)<>3,"CHECK",IF(MAX(MAX(C16:E16),-MIN(C16:E16))<=F16,"PASS","CHECK")),"CHECK") -> PASS | H16: Same number on two pages of the source.
A17: 4 | B17: PAT: p.4 table − p.3 table = 0 | C17: ='Raw Data'!C11-'Raw Data'!C49 -> 0 | D17: ='Raw Data'!D11-'Raw Data'!D49 -> 0 | E17: ='Raw Data'!E11-'Raw Data'!E49 -> 0 | F17: 0.5 | G17: =IFERROR(IF(COUNT(C17:E17)<>3,"CHECK",IF(MAX(MAX(C17:E17),-MIN(C17:E17))<=F17,"PASS","CHECK")),"CHECK") -> PASS | H17: Same number on two pages of the source.
A18: 5 | B18: PBT − (operating profit + other income − finance cost), ₹ crore | C18: ='Raw Data'!C9-('Raw Data'!C7+'Raw Data'!C31*'Raw Data'!C6-'Raw Data'!C8) -> 59.194 | D18: ='Raw Data'!D9-('Raw Data'!D7+'Raw Data'!D31*'Raw Data'!D6-'Raw Data'!D8) -> -52.77 | E18: ='Raw Data'!E9-('Raw Data'!E7+'Raw Data'!E31*'Raw Data'!E6-'Raw Data'!E8) -> 14.22 | F18: ='Financial Calculations'!$C$6*MAX('Raw Data'!$C$6:$E$6) -> 81.495 | G18: =IFERROR(IF(COUNT(C18:E18)<>3,"CHECK",IF(MAX(MAX(C18:E18),-MIN(C18:E18))<=F18,"PASS","CHECK")),"CHECK") -> PASS | H18: Other income is rebuilt from a rounded ratio, so a small gap is expected; tolerance = rounding limit on revenue.
A19: 6 | B19: Operating margin: ROUND(calc, 3) − printed | C19: =ROUND('Raw Data'!C7/'Raw Data'!C6,3)-'Raw Data'!C30 -> 0 | D19: =ROUND('Raw Data'!D7/'Raw Data'!D6,3)-'Raw Data'!D30 -> 0 | E19: =ROUND('Raw Data'!E7/'Raw Data'!E6,3)-'Raw Data'!E30 -> 0 | F19: 1e-06 | G19: =IFERROR(IF(COUNT(C19:E19)<>3,"CHECK",IF(MAX(MAX(C19:E19),-MIN(C19:E19))<=F19,"PASS","CHECK")),"CHECK") -> PASS | H19: Printed ratio is reproducible from the rupee figures.
A20: 7 | B20: PAT margin: ROUND(calc, 3) − printed | C20: =ROUND('Raw Data'!C11/'Raw Data'!C6,3)-'Raw Data'!C35 -> 0 | D20: =ROUND('Raw Data'!D11/'Raw Data'!D6,3)-'Raw Data'!D35 -> 0 | E20: =ROUND('Raw Data'!E11/'Raw Data'!E6,3)-'Raw Data'!E35 -> 0 | F20: 1e-06 | G20: =IFERROR(IF(COUNT(C20:E20)<>3,"CHECK",IF(MAX(MAX(C20:E20),-MIN(C20:E20))<=F20,"PASS","CHECK")),"CHECK") -> PASS | H20: As above.
A21: 8 | B21: Effective tax rate: ROUND(calc, 3) − printed | C21: =ROUND('Raw Data'!C10/'Raw Data'!C9,3)-'Raw Data'!C34 -> 0 | D21: =ROUND('Raw Data'!D10/'Raw Data'!D9,3)-'Raw Data'!D34 -> 0 | E21: =ROUND('Raw Data'!E10/'Raw Data'!E9,3)-'Raw Data'!E34 -> 0 | F21: 1e-06 | G21: =IFERROR(IF(COUNT(C21:E21)<>3,"CHECK",IF(MAX(MAX(C21:E21),-MIN(C21:E21))<=F21,"PASS","CHECK")),"CHECK") -> PASS | H21: As above.
A22: 9 | B22: Tax ÷ revenue: ROUND(calc, 3) − printed | C22: =ROUND('Raw Data'!C10/'Raw Data'!C6,3)-'Raw Data'!C33 -> 0 | D22: =ROUND('Raw Data'!D10/'Raw Data'!D6,3)-'Raw Data'!D33 -> 0 | E22: =ROUND('Raw Data'!E10/'Raw Data'!E6,3)-'Raw Data'!E33 -> 0 | F22: 1e-06 | G22: =IFERROR(IF(COUNT(C22:E22)<>3,"CHECK",IF(MAX(MAX(C22:E22),-MIN(C22:E22))<=F22,"PASS","CHECK")),"CHECK") -> PASS | H22: As above.
A23: 10 | B23: PBT ÷ revenue: ROUND(calc, 3) − printed | C23: =ROUND('Raw Data'!C9/'Raw Data'!C6,3)-'Raw Data'!C32 -> 0 | D23: =ROUND('Raw Data'!D9/'Raw Data'!D6,3)-'Raw Data'!D32 -> 0 | E23: =ROUND('Raw Data'!E9/'Raw Data'!E6,3)-'Raw Data'!E32 -> 0 | F23: 1e-06 | G23: =IFERROR(IF(COUNT(C23:E23)<>3,"CHECK",IF(MAX(MAX(C23:E23),-MIN(C23:E23))<=F23,"PASS","CHECK")),"CHECK") -> PASS | H23: As above.
A24: 11 | B24: Revenue growth: ROUND(calc, 2) − printed | C24: =ROUND('Raw Data'!C6/'Raw Data'!C50-1,2)-'Raw Data'!C45 -> 0 | D24: =ROUND('Raw Data'!D6/'Raw Data'!D50-1,2)-'Raw Data'!D45 -> 0 | E24: =ROUND('Raw Data'!E6/'Raw Data'!E50-1,2)-'Raw Data'!E45 -> 0 | F24: 1e-06 | G24: =IFERROR(IF(COUNT(C24:E24)<>3,"CHECK",IF(MAX(MAX(C24:E24),-MIN(C24:E24))<=F24,"PASS","CHECK")),"CHECK") -> PASS | H24: Printed growth matches the rupee series (uses prior-year revenue from p.3/p.4).
A25: 12 | B25: PAT growth: ROUND(calc, 2) − printed | C25: =ROUND('Raw Data'!C11/'Raw Data'!C51-1,2)-'Raw Data'!C46 -> 0 | D25: =ROUND('Raw Data'!D11/'Raw Data'!D51-1,2)-'Raw Data'!D46 -> 0 | E25: =ROUND('Raw Data'!E11/'Raw Data'!E51-1,2)-'Raw Data'!E46 -> 0 | F25: 1e-06 | G25: =IFERROR(IF(COUNT(C25:E25)<>3,"CHECK",IF(MAX(MAX(C25:E25),-MIN(C25:E25))<=F25,"PASS","CHECK")),"CHECK") -> PASS | H25: As above.
A26: 13 | B26: Market cap ÷ revenue: ROUND(calc, 1) − printed | C26: =ROUND('Raw Data'!C24/'Raw Data'!C6,1)-'Raw Data'!C38 -> 0 | D26: =ROUND('Raw Data'!D24/'Raw Data'!D6,1)-'Raw Data'!D38 -> 0 | E26: =ROUND('Raw Data'!E24/'Raw Data'!E6,1)-'Raw Data'!E38 -> 0 | F26: 1e-06 | G26: =IFERROR(IF(COUNT(C26:E26)<>3,"CHECK",IF(MAX(MAX(C26:E26),-MIN(C26:E26))<=F26,"PASS","CHECK")),"CHECK") -> PASS | H26: Ties the market-capitalisation row to the ratio table.
A27: 14 | B27: Cash + investments ÷ total assets: own − company (pp) | C27: ='Financial Calculations'!C16 -> 0.25657786 | D27: ='Financial Calculations'!D16 -> 0.29578853 | E27: ='Financial Calculations'!E16 -> 0.33306448 | F27: 1 | G27: =IFERROR(IF(COUNT(C27:E27)<>3,"CHECK",IF(MAX(MAX(C27:E27),-MIN(C27:E27))<=F27,"PASS","CHECK")),"CHECK") -> PASS | H27: Own measure should sit within 1 pp of the company's narrower measure.
A28: 15 | B28: Cash + investments ÷ revenue: own − company (pp) | C28: ='Financial Calculations'!C19 -> 0.26547453 | D28: ='Financial Calculations'!D19 -> 0.24521377 | E28: ='Financial Calculations'!E19 -> 0.24720535 | F28: 1 | G28: =IFERROR(IF(COUNT(C28:E28)<>3,"CHECK",IF(MAX(MAX(C28:E28),-MIN(C28:E28))<=F28,"PASS","CHECK")),"CHECK") -> PASS | H28: As above.
A29: 16 | B29: Company cash & investments: ratio×assets vs ratio×revenue | C29: ='Financial Calculations'!C68 -> -66.813 | D29: ='Financial Calculations'!D68 -> 30.818 | E29: ='Financial Calculations'!E68 -> 93.023 | F29: ='Financial Calculations'!$C$6*(MAX('Raw Data'!$C$23:$E$23)+MAX('Raw Data'!$C$6:$E$6)) -> 155.9465 | G29: =IFERROR(IF(COUNT(C29:E29)<>3,"CHECK",IF(MAX(MAX(C29:E29),-MIN(C29:E29))<=F29,"PASS","CHECK")),"CHECK") -> PASS | H29: Two printed ratios imply the same rupee pool within rounding - supports using them.
A30: 17 | B30: Cash + investments not above total assets (excess) | C30: =MAX(0,'Financial Calculations'!C11-'Raw Data'!C23) -> 0 | D30: =MAX(0,'Financial Calculations'!D11-'Raw Data'!D23) -> 0 | E30: =MAX(0,'Financial Calculations'!E11-'Raw Data'!E23) -> 0 | F30: 0 | G30: =IFERROR(IF(COUNT(C30:E30)<>3,"CHECK",IF(MAX(MAX(C30:E30),-MIN(C30:E30))<=F30,"PASS","CHECK")),"CHECK") -> PASS | H30: Plausibility.
A31: 18 | B31: Net current assets not above total assets (excess) | C31: =MAX(0,'Raw Data'!C22-'Raw Data'!C23) -> 0 | D31: =MAX(0,'Raw Data'!D22-'Raw Data'!D23) -> 0 | E31: =MAX(0,'Raw Data'!E22-'Raw Data'!E23) -> 0 | F31: 0 | G31: =IFERROR(IF(COUNT(C31:E31)<>3,"CHECK",IF(MAX(MAX(C31:E31),-MIN(C31:E31))<=F31,"PASS","CHECK")),"CHECK") -> PASS | H31: Plausibility.
A32: 19 | B32: Equity not above total assets (excess) | C32: =MAX(0,'Raw Data'!C15-'Raw Data'!C23) -> 0 | D32: =MAX(0,'Raw Data'!D15-'Raw Data'!D23) -> 0 | E32: =MAX(0,'Raw Data'!E15-'Raw Data'!E23) -> 0 | F32: 0 | G32: =IFERROR(IF(COUNT(C32:E32)<>3,"CHECK",IF(MAX(MAX(C32:E32),-MIN(C32:E32))<=F32,"PASS","CHECK")),"CHECK") -> PASS | H32: Plausibility.
A33: 20 | B33: Derived OCF range ordered (low ≤ central ≤ high; violation) | C33: =MAX(0,'Financial Calculations'!C52-'Financial Calculations'!C51,'Financial Calculations'!C51-'Financial Calculations'!C53) -> 0 | D33: =MAX(0,'Financial Calculations'!D52-'Financial Calculations'!D51,'Financial Calculations'!D51-'Financial Calculations'!D53) -> 0 | E33: =MAX(0,'Financial Calculations'!E52-'Financial Calculations'!E51,'Financial Calculations'!E51-'Financial Calculations'!E53) -> 0 | F33: 0 | G33: =IFERROR(IF(COUNT(C33:E33)<>3,"CHECK",IF(MAX(MAX(C33:E33),-MIN(C33:E33))<=F33,"PASS","CHECK")),"CHECK") -> PASS | H33: Range logic.
A34: 21 | B34: Derived FCF not above derived OCF (excess) | C34: =MAX(0,'Financial Calculations'!C55-'Financial Calculations'!C51) -> 0 | D34: =MAX(0,'Financial Calculations'!D55-'Financial Calculations'!D51) -> 0 | E34: =MAX(0,'Financial Calculations'!E55-'Financial Calculations'!E51) -> 0 | F34: 0 | G34: =IFERROR(IF(COUNT(C34:E34)<>3,"CHECK",IF(MAX(MAX(C34:E34),-MIN(C34:E34))<=F34,"PASS","CHECK")),"CHECK") -> PASS | H34: Capex is positive.
A35: 22 | B35: Debt = 0 (source shows nil) | C35: ='Raw Data'!C16 -> 0 | D35: ='Raw Data'!D16 -> 0 | E35: ='Raw Data'!E16 -> 0 | F35: 0 | G35: =IFERROR(IF(COUNT(C35:E35)<>3,"CHECK",IF(MAX(MAX(C35:E35),-MIN(C35:E35))<=F35,"PASS","CHECK")),"CHECK") -> PASS | H35: Confirms the debt-free reading used in the narrative.
A36: 23 | B36: Completeness: numeric inputs on Raw Data − expected count | C36: =IF(COUNT('Raw Data'!$C$5:$E$58)=132,0,COUNT('Raw Data'!$C$5:$E$58)-132) -> 0 | D36: =0 -> 0 | E36: =0 -> 0 | F36: 0 | G36: =IFERROR(IF(COUNT(C36:E36)<>3,"CHECK",IF(MAX(MAX(C36:E36),-MIN(C36:E36))<=F36,"PASS","CHECK")),"CHECK") -> PASS | H36: Raw Data should contain 132 numeric inputs; shown in the first column only.
A38: Part C - Limitations that apply to every result
A39: 1 | B39: Accounting basis: p.1 says the ratios use consolidated IFRS INR statements; the Historical Data table (p.4) does not name its basis. All figures are used as printed.
A40: 2 | B40: Rounding: ratios are printed to one decimal place (0.1 percentage point), so any rupee figure rebuilt from a ratio can be off by up to +/-0.05 percentage point of the base (about +/-Rs 80 crore on FY25 revenue).
A41: 3 | B41: Non-IFRS measure: the company's 'cash and investments' (p.1) excludes some investments; footnotes on p.1 and p.2 word the exclusion slightly differently.
A42: 4 | B42: Investments are shown as one combined current + non-current line, so cash + investments cannot be treated as a current-asset (short-term) measure.
A43: 5 | B43: Capital expenditure: the file does not say whether it is cash paid or additions in the year, or whether it is net of disposals.
A44: 6 | B44: USD-term ratios: day's sales outstanding and return on equity are computed in US dollars by the company and cannot be reproduced from the rupee figures.
A45: 7 | B45: Three years give only two year-on-year changes; the FY2024-25 jump in operating cash flow ratio may include one-off working-capital or tax timing effects that the file does not disclose.
B47: Manual verification step (recommended): open the PDF and tick each Raw Data row against the page named in column H. The audit checks above prove internal consistency, not that a digit was typed correctly.
